{"type":"PR","pr":{"number":16,"head":"73db87126d87adb3f09614c367adcdbb66ec0451"},"user":"Harrison Milbradt","branch":"cms/fixing-update_rollback_failed-in-serverless","collection":"blog","title":"Fixing UPDATE_ROLLBACK_FAILED in Serverless","description":"Recently, I ran into an issue with deploying my Serverless application.  After a lot of debugging, trial and error, and sweat, I was finally able to come up with a solution to the UPDATE_ROLLBACK_FAILED error.","objects":{"entry":{"path":"src/pages/blog/fixing-update_rollback_failed-in-serverless.md","sha":"fdbfa6d004c84731f6d16f34eeb817ecab331845"},"files":[]},"timeStamp":"2019-11-07T19:29:20.232Z","status":"pending_publish"}